my_test_only/__init__.py
my_test_only/core.py
my_test_only-0.1.0.dist-info/LICENSE
my_test_only-0.1.0.dist-info/METADATA
my_test_only-0.1.0.dist-info/WHEEL
my_test_only-0.1.0.dist-info/top_level.txt
my_test_only-0.1.0.dist-info/RECORD
