Metadata-Version: 2.1
Name: my_test_only
Version: 0.1.0
Summary: A simple Python library for demonstration
Home-page: https://github.com/your_username/my_library
Author: Your Name
Author-email: your_email@example.com
License: MIT
Requires-Python: >=3.6
License-File: LICENSE
